vmware_nsx/__init__.py
vmware_nsx/_i18n.py
vmware_nsx/opts.py
vmware_nsx/plugin.py
vmware_nsx/version.py
vmware_nsx/api_client/__init__.py
vmware_nsx/api_client/base.py
vmware_nsx/api_client/client.py
vmware_nsx/api_client/eventlet_client.py
vmware_nsx/api_client/eventlet_request.py
vmware_nsx/api_client/exception.py
vmware_nsx/api_client/request.py
vmware_nsx/api_client/version.py
vmware_nsx/api_replay/__init__.py
vmware_nsx/api_replay/cli.py
vmware_nsx/api_replay/client.py
vmware_nsx/api_replay/utils.py
vmware_nsx/common/__init__.py
vmware_nsx/common/availability_zones.py
vmware_nsx/common/config.py
vmware_nsx/common/driver_api.py
vmware_nsx/common/exceptions.py
vmware_nsx/common/l3_rpc_agent_api.py
vmware_nsx/common/locking.py
vmware_nsx/common/managers.py
vmware_nsx/common/nsx_constants.py
vmware_nsx/common/nsxv_constants.py
vmware_nsx/common/profile.py
vmware_nsx/common/utils.py
vmware_nsx/db/__init__.py
vmware_nsx/db/db.py
vmware_nsx/db/distributedrouter.py
vmware_nsx/db/extended_security_group.py
vmware_nsx/db/extended_security_group_rule.py
vmware_nsx/db/lsn_db.py
vmware_nsx/db/maclearning.py
vmware_nsx/db/nsx_models.py
vmware_nsx/db/nsx_portbindings_db.py
vmware_nsx/db/nsxrouter.py
vmware_nsx/db/nsxv_db.py
vmware_nsx/db/nsxv_models.py
vmware_nsx/db/routertype.py
vmware_nsx/db/vcns_models.py
vmware_nsx/db/vnic_index_db.py
vmware_nsx/db/migration/__init__.py
vmware_nsx/db/migration/alembic_migrations/__init__.py
vmware_nsx/db/migration/alembic_migrations/env.py
vmware_nsx/db/migration/alembic_migrations/script.py.mako
vmware_nsx/db/migration/alembic_migrations/versions/CONTRACT_HEAD
vmware_nsx/db/migration/alembic_migrations/versions/EXPAND_HEAD
vmware_nsx/db/migration/alembic_migrations/versions/kilo_release.py
vmware_nsx/db/migration/alembic_migrations/versions/liberty/contract/393bf843b96_initial_liberty_no_op_contract_script.py
vmware_nsx-17.0.0.dist-info/DESCRIPTION.rst
vmware_nsx-17.0.0.dist-info/METADATA
vmware_nsx-17.0.0.dist-info/RECORD
vmware_nsx-17.0.0.dist-info/WHEEL
vmware_nsx-17.0.0.dist-info/entry_points.txt
vmware_nsx-17.0.0.dist-info/metadata.json
vmware_nsx-17.0.0.dist-info/pbr.json
vmware_nsx-17.0.0.dist-info/top_level.txt
