Metadata-Version: 2.0
Name: vmware-nsx
Version: 17.0.0
Summary: VMware NSX library for OpenStack projects
Home-page: https://launchpad.net/vmware-nsx
Author: OpenStack
Author-email: openstack-discuss@lists.openstack.org
License: UNKNOWN
Platform: UNKNOWN
Classifier: Environment :: OpenStack
Classifier: Intended Audience :: Information Technology
Classifier: Intended Audience :: System Administrators
Classifier: License :: OSI Approved :: Apache Software License
Classifier: Operating System :: POSIX :: Linux
Classifier: Programming Language :: Python :: 3
Classifier: Programming Language :: Python :: 3.6
Classifier: Programming Language :: Python :: 3.7
Requires-Python: >=3.6
Requires-Dist: PrettyTable (<0.8,>=0.7.2)
Requires-Dist: SQLAlchemy (!=1.1.5,!=1.1.6,!=1.1.7,!=1.1.8,>=1.2.0)
Requires-Dist: decorator (>=4.4.1)
Requires-Dist: eventlet (>=0.24.1)
Requires-Dist: httplib2 (>=0.9.1)
Requires-Dist: netaddr (>=0.7.18)
Requires-Dist: networking-l2gw (>=16.0.0)
Requires-Dist: networking-sfc (>=10.0.0.0)
Requires-Dist: neutron-dynamic-routing (>=16.0.0.0)
Requires-Dist: neutron-fwaas (>=16.0.0.0)
Requires-Dist: neutron-lib (>=2.0.0)
Requires-Dist: neutron-vpnaas (>=17.0.0.0)
Requires-Dist: neutron (>=17.0.0.0)
Requires-Dist: octavia-lib (>=1.3.1)
Requires-Dist: osc-lib (>=1.14.0)
Requires-Dist: oslo.concurrency (>=3.26.0)
Requires-Dist: oslo.config (>=5.2.0)
Requires-Dist: oslo.context (>=2.19.2)
Requires-Dist: oslo.db (>=4.44.0)
Requires-Dist: oslo.i18n (>=3.15.3)
Requires-Dist: oslo.log (>=3.36.0)
Requires-Dist: oslo.policy (>=1.30.0)
Requires-Dist: oslo.serialization (>=2.28.1)
Requires-Dist: oslo.service (>=1.31.0)
Requires-Dist: oslo.utils (>=3.33.0)
Requires-Dist: oslo.vmware (>=2.17.0)
Requires-Dist: paramiko (>=2.4.0)
Requires-Dist: pbr (>=4.0.0)
Requires-Dist: python-openstackclient (>=5.3.0)
Requires-Dist: requests (>=2.14.2)
Requires-Dist: stevedore (>=1.20.0)
Requires-Dist: tenacity (>=5.0.2)
Requires-Dist: tooz (>=1.58.0)
Requires-Dist: vmware-nsxlib (>=16.0.0)
